{"script_exec": {"lst_update": "2023-07-23 18:30:34 UTC", "lst_date": "2023-07-23 18:30:34 UTC", "from": "py", "msg_txt": ""}, "status": {"lst_update": "2023-07-23 18:35:28 UTC", "lst_date": "23-07-2023", "from": "py", "msg_txt": {"lst": "23-07-2023", "status": "long", "status_prev": "neutral", "action": "-", "success": "yes"}}, "posttrades": {"lst_update": "2023-07-23 18:35:51 UTC", "lst_date": "23-07-2023", "from": "py", "msg_txt": "POST TRADES OK:\nscripts : | 23 Jul 2023 18:35"}, "last_execution": {"lst_update": "2023-07-23 18:35:28 UTC", "lst_date": "23-07-2023", "from": "py", "msg_txt": "EXECUTION TRADES OK:\nscripts : | 23 Jul 2023 18:35:execution\n***************************\nTrades of the day\nin$\nas of: 23Jul 18:30>>18:35 (#trades: 3)\ntrade net: +159.0 (+53.9%), trade gross: +159.0 (+53.9%), BUY: +159.0 (+53.9%), SELL: +0.0 (+0.0%)\nfees: $ 0.025 (1.6bp)"}, "bt_update": {"lst_update": "2023-07-23 18:35:43 UTC", "lst_date": "2023-07-23 18:35:43", "from": "py", "msg_txt": ""}}