{"0_dowload_data":{"lst_update":"2023-11-01 11:41:29 UTC","lst_date":"01 Nov 23","source":"heroku.python","msg_txt":""},"1_compute_mozaic_allocation":{"lst_update":"2023-11-01 11:41:36 UTC","lst_date":"01 Nov 23","source":"heroku.python","msg_txt":""},"2_compute_mozaic_bt_ytd":{"lst_update":"2023-11-01 11:41:50 UTC","lst_date":"01 Nov 23","source":"heroku.python","msg_txt":""},"3_0_orderbook_forwebsite":{"lst_update":"2023-11-01 11:42:15 UTC","lst_date":"2023-11-01","source":"heroku.python","msg_txt":"NAV, 01Nov@11:41\nAUM_t: 911.53, AUM_tm1: 922.87\nP&L B:-11.3$(-1.2%), BTC: 34412.0$(-0.7%)\n\nPerformance attribution\nPnL: -11.2$, PnL_tm1: -11.2$, PnL_trd: +0.0$, tc_usdt: 0.0, \u03b5: -0.12\nd_t: 01Nov 11:41, d_tm1: 31Oct 23:59, d_trd: \n\nWallet:\nas of: 01 Nov 11:41\nAUMs: $ 912, P&L[U]: $ 179.5\nsum w%: 89%, sum w%>0: 96%, sum w%<0: -7%\n--------------------------\nPerformance report\n--------------------------\nBinance Official\n1D: -1.2%, WtD: +2.9%, 7D: +3.2%, MtD: -1.2%, s. 18Feb23: +4.4%\nBacktest\n1D: -1.3%, WtD: +2.8%, 7D: +3.2%, MtD: -1.3%, s. 18Feb23: -15.1%\nBitcoin\n1D: -0.7%, WtD: -0.3%, 7D: -0.2%, MtD: -0.7%, s. 18Feb23: +39.7%\nCryptosAll\n1D: -1.4%, WtD: +1.0%, 7D: +2.8%, MtD: -1.4%, s. 18Feb23: -13.0%\ntracking_error\n1D: +0.0%, WtD: +0.1%, 7D: +0.0%, MtD: +0.0%, s. 18Feb23: +23.0%\n----------------------------"},"5_execute_futures":{"lst_update":"2023-10-31 14:04:09 UTC","lst_date":"2023-10-31","source":"heroku.python","msg_txt":"EXECUTION TRADES OK:\nscripts :2023-10-31 13:41:25 UTC:0_dowload_data | 2023-10-31 14:00:49 UTC:1_compute_mozaic_allocation | 31 Oct 2023 14:04:5_execute_futures\n***************************\nTrades of the day\nin$\nas of: 31Oct 14:01>>14:03 (#trades: 8)\ntrade net: $ -28 (-3%), trade gross: $ 180 (19%), BUY: $ 76 (8%), SELL: $ -104 (-11%)\nfees: $ 0.036 (2.0bp)"},"6_post_trades":{"lst_update":"2023-11-01 11:42:26 UTC","lst_date":"31Oct 14:01>>14:03","source":"heroku.python","msg_txt":"Trades of the day\nin$\nas of: 31Oct 14:01>>14:03 (#trades: 8)\ntrade net: $ -28 (-3%), trade gross: $ 180 (19%), BUY: $ 76 (8%), SELL: $ -104 (-11%)\nfees: $ 0.036 (2.0bp)\n                in$ | in bp vs. 180 traded | in bp vs. 912 AUMs\nPnLvsLast      -3.9 | -215.0  | -43.0  \nPnLvsArrival   +0.1 | +6.0    | +1.0   \nrealizedPnl    +12.2 | +677.0  | +134.0 Trades: \nFilled #8\n______________________________________________\n                  quoteQty$ | PnL Arrival\/Last \n______________________________________________\nADA  :-40   @0.2939 | -12 $ | +0.0 \/ +0.3\nATOM :+5.41 @8.096  | +44 $ | +0.0 \/ -2.5\nBCH  :-0.06 @242.33 | -14 $ | -0.0 \/ +0.2\nDOGE :-144  @0.0684 | -10 $ | +0.0 \/ +0.3\nMATIC:-51   @0.6381 | -33 $ | +0.0 \/ +0.6\nSOL  :-1    @35.968 | -36 $ | +0.1 \/ -3.0\nXMR  :+0.08 @169.44 | +13 $ | -0.0 \/ +0.1\nXRP  :+31.7 @0.5949 | +19 $ | +0.0 \/ +0.2"},"6_send_mailrecap":{"lst_update":"2023-11-01 09:47:18 UTC","lst_date":"","source":"heroku.python","msg_txt":"OK | not sent to tristan | sent to tristan : 2023-10-31 17:44 UTC"},"6bis_tradesday":{"lst_update":"2023-10-31 20:00:49 UTC","lst_date":"31Oct 18:32>>18:33","source":"heroku.python","msg_txt":"\n-------\nMOZAIC\nas of: 31Oct 14:01>>14:03 (#trades: 8)\ntrade net: $ -28 (-3%), trade gross: $ 180 (19%), BUY: $ 76 (8%), SELL: $ -104 (-11%)\nfees: $ 0.036 (2.0bp)\n-------\nON\nas of: 31Oct 18:32>>18:33 (#trades: 3)\ntrade net: $ 129 (14%), trade gross: $ 129 (14%), BUY: $ 129 (14%), SELL: $ 0 (0%)\nfees: $ 0.026 (2.0bp)\n                in$ | vs. 309 traded | vs. 906 AUMs\nPnLvsLast      -0bp | -15bp   | -5bp   \nrealizedPnl    +12bp | +395bp  | +135bp Trades: \nFilled #10\n______________________________________________\n                  quoteQty$ | PnL Last \n______________________________________________\nADA  :-40   @0.2939 | -12 $ |  +0.1\nATOM :+5.41 @8.096  | +44 $ |  -1.3\nBCH  :-0.06 @242.33 | -14 $ |  +0.0\nBTC  :+0    @34374. | +34 $ |  +0.0\nDOGE :-144  @0.0684 | -10 $ |  +0.1\nETH  :+0.03 @1800.2 | +47 $ |  +0.3\nMATIC:-51   @0.6381 | -33 $ |  +0.4\nSOL  :-1    @35.968 | -36 $ |  -0.3\nXMR  :+0.08 @169.44 | +13 $ |  +0.2\nXRP  :+111.1@0.5981 | +66 $ |  +0.0\nTrades Line by line: \nFilled #12\n___________________________________________________________________________________________\n31-10 18:33:24  ON      BUY   XRP   +79.4 @0.6     | $+47.        U:-0.1 Lst:0.5985   \n31-10 18:32:45  ON      BUY   ETH   +0.02 @1800.2  | $+43.        U:+0.2 Lst:1810.98   \n31-10 18:32:45  ON      BUY   ETH   +0    @1800.2  | $+3.6        U:+0.0 Lst:1810.98   \n31-10 18:32:35  ON      BUY   BTC   +0    @34374.  | $+34.        U:+0.0 Lst:34530.6   \n31-10 14:03:57  MOZAIC  BUY   XMR   +0.08 @169.44  | $+13.        U:+0.1 Lst:171.61   \n31-10 14:02:51  MOZAIC  SELL  DOGE  -144  @0.07    | $-9.8 R:-0.4 U:+0.2 Lst:0.06812   \n31-10 14:02:51  MOZAIC  SELL  BCH   -0.06 @242.33  | $-14. R:+0.3 U:+0.0 Lst:241.95   \n31-10 14:02:37  MOZAIC  BUY   XRP   +31.7 @0.59    | $+18. R:-1.3 U:+0.2 Lst:0.5985   \n31-10 14:02:19  MOZAIC  SELL  ADA   -40   @0.29    | $-11.        U:-0.0 Lst:0.2919   \n31-10 14:02:13  MOZAIC  SELL  MATIC -51   @0.64    | $-32. R:+1.7 U:+0.5 Lst:0.6296   \n31-10 14:01:44  MOZAIC  SELL  SOL   -1    @35.97   | $-35. R:+13. U:-0.2 Lst:36.255   \n31-10 14:01:16  MOZAIC  BUY   ATOM  +5.41 @8.1     | $+43. R:-1.2 U:-1.2 Lst:7.861   \n___________________________________________________________________________________________"},"8_bt_btcXalt":{"lst_update":"2023-11-01 07:45:17 UTC","lst_date":"20231101","source":"heroku.python","msg_txt":"Btx X Alt Coins, activation \nAs of 2023-11-01\n30,60  BTC-next top10    1.0\n30,60  BTC-next top20    1.0\n----------------------------\nExposure to BTC x ALT : 100%\n----------------------------"},"9_bt_recap":{"lst_update":"2023-10-31 18:00:00 UTC","lst_date":"20231030","source":"sebas.jupyter","msg_txt":"ok"},"9_pygithub_4website":{"lst_update":"2023-11-01 09:47:14 UTC","lst_date":"","source":"heroku.python","msg_txt":""},"_7_crypto_map":{"lst_update":"2023-10-31 19:42:25 UTC","lst_date":"31 Oct 2023","source":"heroku.python","msg_txt":""}}