{"cols": [{"id": "as of 08May 13:23", "label": "as of 08May 13:23", "type": "string"}, {"id": "PnL_D", "label": "PnL_D", "type": "number"}], "rows": [{"c": [{"v": "BNB"}, {"v": 2886.3}]}, {"c": [{"v": "NEAR"}, {"v": 364.9}]}, {"c": [{"v": "TRX"}, {"v": 2481.6}]}, {"c": [{"v": "SOL"}, {"v": -1564.6}]}, {"c": [{"v": "TON"}, {"v": 2245.4}]}, {"c": [{"v": "DOT"}, {"v": -279.5}]}, {"c": [{"v": "XRP"}, {"v": -94.5}]}, {"c": [{"v": "DOGE"}, {"v": -328.5}]}, {"c": [{"v": "LTC"}, {"v": -68.9}]}, {"c": [{"v": "ETH"}, {"v": -28.3}]}, {"c": [{"v": "BCH"}, {"v": 756.9}]}, {"c": [{"v": "MATIC"}, {"v": 678.2}]}, {"c": [{"v": "ICP"}, {"v": 556.4}]}, {"c": [{"v": "ADA"}, {"v": 175.0}]}, {"c": [{"v": "BTC"}, {"v": -2736.9}]}, {"c": [{"v": "NEAR"}, {"v": -33.8}]}, {"c": [{"v": "MATIC"}, {"v": 306.7}]}, {"c": [{"v": "ICP"}, {"v": 236.7}]}, {"c": [{"v": "DOT"}, {"v": 59.8}]}, {"c": [{"v": "LINK"}, {"v": 181.5}]}, {"c": [{"v": "BCH"}, {"v": 435.8}]}, {"c": [{"v": "TRX"}, {"v": -372.2}]}, {"c": [{"v": "LTC"}, {"v": -88.2}]}, {"c": [{"v": "TON"}, {"v": -820.4}]}, {"c": [{"v": "AVAX"}, {"v": 1011.8}]}, {"c": [{"v": "SHIB"}, {"v": 519.9}]}, {"c": [{"v": "DOGE"}, {"v": 349.2}]}, {"c": [{"v": "SOL"}, {"v": 602.3}]}, {"c": [{"v": "ADA"}, {"v": 173.4}]}, {"c": [{"v": "BNB"}, {"v": -875.8}]}, {"c": [{"v": "XRP"}, {"v": 132.1}]}]}