{"cols": [{"id": "as of 26Sep 22:24", "label": "as of 26Sep 22:24", "type": "string"}, {"id": "PnL_D", "label": "PnL_D", "type": "number"}], "rows": [{"c": [{"v": "NEAR"}, {"v": 23052.2}]}, {"c": [{"v": "AVAX"}, {"v": 15403.4}]}, {"c": [{"v": "SUI"}, {"v": 232.1}]}, {"c": [{"v": "BNB"}, {"v": 1632.0}]}, {"c": [{"v": "SHIB"}, {"v": 17542.4}]}, {"c": [{"v": "BTC"}, {"v": 1405.5}]}, {"c": [{"v": "LINK"}, {"v": 1621.7}]}, {"c": [{"v": "SOL"}, {"v": 1782.9}]}, {"c": [{"v": "TON"}, {"v": 298.7}]}, {"c": [{"v": "ETH"}, {"v": 542.1}]}, {"c": [{"v": "LTC"}, {"v": 512.0}]}, {"c": [{"v": "ADA"}, {"v": 619.9}]}, {"c": [{"v": "DOGE"}, {"v": 771.0}]}, {"c": [{"v": "DOT"}, {"v": -516.4}]}, {"c": [{"v": "TRX"}, {"v": -355.6}]}, {"c": [{"v": "BTC"}, {"v": 17841.4}]}, {"c": [{"v": "ETH"}, {"v": 1504.3}]}, {"c": [{"v": "SOL"}, {"v": 530.9}]}, {"c": [{"v": "NEAR"}, {"v": -1237.7}]}, {"c": [{"v": "DOT"}, {"v": -598.9}]}, {"c": [{"v": "BCH"}, {"v": -471.2}]}, {"c": [{"v": "LTC"}, {"v": -544.3}]}, {"c": [{"v": "TRX"}, {"v": -1009.3}]}, {"c": [{"v": "XRP"}, {"v": -684.3}]}, {"c": [{"v": "DOGE"}, {"v": -3344.6}]}, {"c": [{"v": "ADA"}, {"v": -2276.2}]}, {"c": [{"v": "LINK"}, {"v": -1628.0}]}, {"c": [{"v": "TON"}, {"v": -425.6}]}, {"c": [{"v": "SHIB"}, {"v": -8693.6}]}, {"c": [{"v": "BNB"}, {"v": -767.8}]}, {"c": [{"v": "AVAX"}, {"v": -3448.0}]}]}