{"cols": [{"id": "as of 06May 14:23", "label": "as of 06May 14:23", "type": "string"}, {"id": "PnL_D", "label": "PnL_D", "type": "number"}], "rows": [{"c": [{"v": "TRX"}, {"v": -2579.9}]}, {"c": [{"v": "NEAR"}, {"v": -703.6}]}, {"c": [{"v": "BNB"}, {"v": -131.6}]}, {"c": [{"v": "TON"}, {"v": 268.7}]}, {"c": [{"v": "DOGE"}, {"v": -448.4}]}, {"c": [{"v": "SOL"}, {"v": 3393.7}]}, {"c": [{"v": "DOT"}, {"v": -600.6}]}, {"c": [{"v": "AVAX"}, {"v": 494.0}]}, {"c": [{"v": "SHIB"}, {"v": -60.4}]}, {"c": [{"v": "LINK"}, {"v": 634.2}]}, {"c": [{"v": "XRP"}, {"v": 98.3}]}, {"c": [{"v": "ICP"}, {"v": -323.4}]}, {"c": [{"v": "BTC"}, {"v": -26.8}]}, {"c": [{"v": "LTC"}, {"v": -89.5}]}, {"c": [{"v": "ADA"}, {"v": -294.8}]}, {"c": [{"v": "BCH"}, {"v": -447.9}]}, {"c": [{"v": "BTC"}, {"v": 1323.2}]}, {"c": [{"v": "MATIC"}, {"v": -127.6}]}, {"c": [{"v": "NEAR"}, {"v": 74.7}]}, {"c": [{"v": "DOT"}, {"v": 233.0}]}, {"c": [{"v": "ICP"}, {"v": -417.6}]}, {"c": [{"v": "BCH"}, {"v": -140.4}]}, {"c": [{"v": "LINK"}, {"v": -575.8}]}, {"c": [{"v": "TRX"}, {"v": 339.8}]}, {"c": [{"v": "LTC"}, {"v": -55.8}]}, {"c": [{"v": "TON"}, {"v": -78.0}]}, {"c": [{"v": "AVAX"}, {"v": -744.6}]}, {"c": [{"v": "DOGE"}, {"v": 297.6}]}, {"c": [{"v": "SHIB"}, {"v": 108.2}]}, {"c": [{"v": "SOL"}, {"v": -2751.9}]}, {"c": [{"v": "ADA"}, {"v": -408.4}]}, {"c": [{"v": "BNB"}, {"v": 51.4}]}, {"c": [{"v": "XRP"}, {"v": -386.7}]}]}