{"cols": [{"id": "as of 30Dec 18:24", "label": "as of 30Dec 18:24", "type": "string"}, {"id": "totrade_w", "label": "totrade_w", "type": "number"}], "rows": [{"c": [{"v": "BTC"}, {"v": -9.25}]}, {"c": [{"v": "ETH"}, {"v": -7.56}]}, {"c": [{"v": "AAVE"}, {"v": -3.91}]}, {"c": [{"v": "TON"}, {"v": -2.13}]}, {"c": [{"v": "SOL"}, {"v": -1.77}]}, {"c": [{"v": "SUI"}, {"v": -1.35}]}, {"c": [{"v": "TRX"}, {"v": -0.65}]}, {"c": [{"v": "DOT"}, {"v": -0.54}]}, {"c": [{"v": "XRP"}, {"v": -0.52}]}, {"c": [{"v": "LINK"}, {"v": -0.43}]}, {"c": [{"v": "ADA"}, {"v": -0.26}]}, {"c": [{"v": "XLM"}, {"v": -0.12}]}, {"c": [{"v": "BNB"}, {"v": 0.19}]}, {"c": [{"v": "1000SHIB"}, {"v": 0.23}]}, {"c": [{"v": "DOGE"}, {"v": 0.36}]}, {"c": [{"v": "HBAR"}, {"v": 0.4}]}, {"c": [{"v": "AVAX"}, {"v": 0.54}]}, {"c": [{"v": "NEAR"}, {"v": 0.76}]}, {"c": [{"v": "APT"}, {"v": 0.8}]}, {"c": [{"v": "1000PEPE"}, {"v": 1.07}]}, {"c": [{"v": "BCH"}, {"v": 1.25}]}]}