{"cols": [{"id": "as of 10Jun 13:07", "label": "as of 10Jun 13:07", "type": "string"}, {"id": "w% current", "label": "w% current", "type": "number"}, {"id": "w% target", "label": "w% target", "type": "number"}], "rows": [{"c": [{"v": "BTC"}, {"v": 51.4}, {"v": 53.0}]}, {"c": [{"v": "ETH"}, {"v": 12.93}, {"v": 10.0}]}, {"c": [{"v": "BNB"}, {"v": 11.1}, {"v": 11.58}]}, {"c": [{"v": "TON"}, {"v": 10.12}, {"v": 11.58}]}, {"c": [{"v": "UNI"}, {"v": 8.9}, {"v": 9.049999999999999}]}, {"c": [{"v": "1000PEPE"}, {"v": 6.260000000000001}, {"v": 3.01}]}, {"c": [{"v": "BCH"}, {"v": 2.02}, {"v": 1.39}]}, {"c": [{"v": "LTC"}, {"v": 0.0}, {"v": -2.08}]}, {"c": [{"v": "TRX"}, {"v": -0.62}, {"v": 4.31}]}, {"c": [{"v": "ICP"}, {"v": -2.31}, {"v": 0.0}]}, {"c": [{"v": "MATIC"}, {"v": -2.88}, {"v": -4.52}]}, {"c": [{"v": "DOGE"}, {"v": -3.9899999999999998}, {"v": -7.340000000000001}]}, {"c": [{"v": "SOL"}, {"v": -4.05}, {"v": -4.42}]}, {"c": [{"v": "XRP"}, {"v": -4.06}, {"v": -5.25}]}, {"c": [{"v": "1000SHIB"}, {"v": -4.5}, {"v": -6.09}]}, {"c": [{"v": "ADA"}, {"v": -4.71}, {"v": -4.42}]}, {"c": [{"v": "DOT"}, {"v": -4.91}, {"v": -4.52}]}, {"c": [{"v": "NEAR"}, {"v": -5.48}, {"v": -7.32}]}, {"c": [{"v": "AVAX"}, {"v": -7.53}, {"v": -8.57}]}]}