{"cols": [{"id": "as of 20Feb 13:23", "label": "as of 20Feb 13:23", "type": "string"}, {"id": "totrade_w", "label": "totrade_w", "type": "number"}], "rows": [{"c": [{"v": "BTC"}, {"v": -31.48}]}, {"c": [{"v": "ETH"}, {"v": -3.07}]}, {"c": [{"v": "LTC"}, {"v": -2.65}]}, {"c": [{"v": "SOL"}, {"v": -2.61}]}, {"c": [{"v": "BNB"}, {"v": -1.97}]}, {"c": [{"v": "UNI"}, {"v": -1.25}]}, {"c": [{"v": "LINK"}, {"v": -1.09}]}, {"c": [{"v": "TON"}, {"v": -0.17}]}, {"c": [{"v": "SUI"}, {"v": -0.17}]}, {"c": [{"v": "OM"}, {"v": -0.05}]}, {"c": [{"v": "BCH"}, {"v": 0.14}]}, {"c": [{"v": "DOT"}, {"v": 0.3}]}, {"c": [{"v": "1000SHIB"}, {"v": 1.47}]}, {"c": [{"v": "DOGE"}, {"v": 1.83}]}, {"c": [{"v": "ADA"}, {"v": 2.17}]}, {"c": [{"v": "TRX"}, {"v": 2.38}]}, {"c": [{"v": "AVAX"}, {"v": 2.47}]}, {"c": [{"v": "HBAR"}, {"v": 3.29}]}, {"c": [{"v": "XLM"}, {"v": 4.68}]}, {"c": [{"v": "XRP"}, {"v": 7.58}]}]}