{"cols": [{"id": "as of 09Apr 15:23", "label": "as of 09Apr 15:23", "type": "string"}, {"id": "PnL_D", "label": "PnL_D", "type": "number"}], "rows": [{"c": [{"v": "BCH"}, {"v": 514.5}]}, {"c": [{"v": "ICP"}, {"v": -6545.2}]}, {"c": [{"v": "ETH"}, {"v": -3495.5}]}, {"c": [{"v": "BTC"}, {"v": -1847.7}]}, {"c": [{"v": "LTC"}, {"v": -2917.1}]}, {"c": [{"v": "SOL"}, {"v": -2533.1}]}, {"c": [{"v": "BNB"}, {"v": -721.5}]}, {"c": [{"v": "NEAR"}, {"v": -436.3}]}, {"c": [{"v": "DOGE"}, {"v": -2432.8}]}, {"c": [{"v": "AVAX"}, {"v": -1245.1}]}, {"c": [{"v": "XRP"}, {"v": 39.6}]}, {"c": [{"v": "TRX"}, {"v": 110.8}]}, {"c": [{"v": "UNI"}, {"v": 1223.3}]}, {"c": [{"v": "DOT"}, {"v": 1162.3}]}, {"c": [{"v": "APT"}, {"v": 2818.1}]}, {"c": [{"v": "LINK"}, {"v": 1384.8}]}, {"c": [{"v": "ADA"}, {"v": 1070.8}]}, {"c": [{"v": "MATIC"}, {"v": 1800.7}]}, {"c": [{"v": "BTC"}, {"v": -18183.1}]}, {"c": [{"v": "NEAR"}, {"v": 68.8}]}, {"c": [{"v": "LTC"}, {"v": 490.6}]}, {"c": [{"v": "ICP"}, {"v": 721.6}]}, {"c": [{"v": "DOT"}, {"v": 428.1}]}, {"c": [{"v": "UNI"}, {"v": 558.6}]}, {"c": [{"v": "MATIC"}, {"v": 501.5}]}, {"c": [{"v": "LINK"}, {"v": 582.6}]}, {"c": [{"v": "TRX"}, {"v": 281.2}]}, {"c": [{"v": "DOGE"}, {"v": 1519.5}]}, {"c": [{"v": "SHIB"}, {"v": 1080.2}]}, {"c": [{"v": "TON"}, {"v": -1053.2}]}, {"c": [{"v": "AVAX"}, {"v": 1544.6}]}, {"c": [{"v": "BCH"}, {"v": -79.1}]}, {"c": [{"v": "SOL"}, {"v": 1678.7}]}, {"c": [{"v": "XRP"}, {"v": -120.9}]}, {"c": [{"v": "BNB"}, {"v": 611.2}]}, {"c": [{"v": "ADA"}, {"v": 1031.3}]}]}