{"cols": [{"id": "as of 25Nov 11:26", "label": "as of 25Nov 11:26", "type": "string"}, {"id": "totrade_w", "label": "totrade_w", "type": "number"}], "rows": [{"c": [{"v": "BTC"}, {"v": -22.37}]}, {"c": [{"v": "ETH"}, {"v": -11.22}]}, {"c": [{"v": "SOL"}, {"v": -5.11}]}, {"c": [{"v": "ADA"}, {"v": -3.93}]}, {"c": [{"v": "DOGE"}, {"v": -2.6}]}, {"c": [{"v": "XLM"}, {"v": -2.6}]}, {"c": [{"v": "XRP"}, {"v": -1.42}]}, {"c": [{"v": "HBAR"}, {"v": -0.8}]}, {"c": [{"v": "SUI"}, {"v": -0.26}]}, {"c": [{"v": "1000PEPE"}, {"v": -0.09}]}, {"c": [{"v": "LTC"}, {"v": 0.52}]}, {"c": [{"v": "TRX"}, {"v": 0.68}]}, {"c": [{"v": "AVAX"}, {"v": 0.72}]}, {"c": [{"v": "1000SHIB"}, {"v": 0.72}]}, {"c": [{"v": "TON"}, {"v": 0.88}]}, {"c": [{"v": "BNB"}, {"v": 1.01}]}, {"c": [{"v": "POL"}, {"v": 1.89}]}, {"c": [{"v": "DOT"}, {"v": 4.67}]}]}