{"cols": [{"id": "as of 28Jun 19:23", "label": "as of 28Jun 19:23", "type": "string"}, {"id": "PnL_D", "label": "PnL_D", "type": "number"}], "rows": [{"c": [{"v": "TON"}, {"v": -12772.2}]}, {"c": [{"v": "TRX"}, {"v": 2168.3}]}, {"c": [{"v": "1000PEPE"}, {"v": -9534.3}]}, {"c": [{"v": "DOT"}, {"v": -400.7}]}, {"c": [{"v": "BNB"}, {"v": -1074.0}]}, {"c": [{"v": "UNI"}, {"v": -1381.1}]}, {"c": [{"v": "XRP"}, {"v": -33.8}]}, {"c": [{"v": "NEAR"}, {"v": -906.7}]}, {"c": [{"v": "LTC"}, {"v": -3.6}]}, {"c": [{"v": "LINK"}, {"v": 576.6}]}, {"c": [{"v": "BTC"}, {"v": 514.3}]}, {"c": [{"v": "AVAX"}, {"v": -120.6}]}, {"c": [{"v": "DOGE"}, {"v": 677.6}]}, {"c": [{"v": "MATIC"}, {"v": 334.9}]}, {"c": [{"v": "BCH"}, {"v": 142.9}]}, {"c": [{"v": "SHIB"}, {"v": 1320.8}]}, {"c": [{"v": "BTC"}, {"v": -11403.5}]}, {"c": [{"v": "UNI"}, {"v": 381.9}]}, {"c": [{"v": "NEAR"}, {"v": 553.9}]}, {"c": [{"v": "MATIC"}, {"v": 163.3}]}, {"c": [{"v": "BCH"}, {"v": 41.9}]}, {"c": [{"v": "LTC"}, {"v": -5.6}]}, {"c": [{"v": "LINK"}, {"v": 617.0}]}, {"c": [{"v": "DOT"}, {"v": 105.1}]}, {"c": [{"v": "SHIB"}, {"v": 906.7}]}, {"c": [{"v": "TON"}, {"v": 1398.4}]}, {"c": [{"v": "DOGE"}, {"v": 894.2}]}, {"c": [{"v": "SOL"}, {"v": 1897.7}]}, {"c": [{"v": "ADA"}, {"v": -186.2}]}, {"c": [{"v": "BNB"}, {"v": 661.6}]}, {"c": [{"v": "AVAX"}, {"v": -187.4}]}, {"c": [{"v": "TRX"}, {"v": -494.0}]}, {"c": [{"v": "XRP"}, {"v": 53.1}]}]}