{"cols": [{"id": "as of 25Feb 17:24", "label": "as of 25Feb 17:24", "type": "string"}, {"id": "PnL_D", "label": "PnL_D", "type": "number"}], "rows": [{"c": [{"v": "LTC"}, {"v": -8312.9}]}, {"c": [{"v": "BNB"}, {"v": -65.8}]}, {"c": [{"v": "OM"}, {"v": -12674.0}]}, {"c": [{"v": "TRX"}, {"v": -11855.5}]}, {"c": [{"v": "BTC"}, {"v": -5546.6}]}, {"c": [{"v": "DOT"}, {"v": 924.2}]}, {"c": [{"v": "ETH"}, {"v": -1323.6}]}, {"c": [{"v": "BCH"}, {"v": 740.2}]}, {"c": [{"v": "UNI"}, {"v": 387.1}]}, {"c": [{"v": "DOGE"}, {"v": 1485.5}]}, {"c": [{"v": "AVAX"}, {"v": 2108.5}]}, {"c": [{"v": "HBAR"}, {"v": 5143.5}]}, {"c": [{"v": "LINK"}, {"v": 3349.8}]}, {"c": [{"v": "SOL"}, {"v": -2676.0}]}, {"c": [{"v": "BTC"}, {"v": -62075.1}]}, {"c": [{"v": "ETH"}, {"v": -2705.1}]}, {"c": [{"v": "DOT"}, {"v": -273.1}]}, {"c": [{"v": "LTC"}, {"v": 676.4}]}, {"c": [{"v": "SHIB"}, {"v": -553.7}]}, {"c": [{"v": "HBAR"}, {"v": 1468.0}]}, {"c": [{"v": "TON"}, {"v": -1040.4}]}, {"c": [{"v": "SUI"}, {"v": -1256.0}]}, {"c": [{"v": "AVAX"}, {"v": 1661.4}]}, {"c": [{"v": "LINK"}, {"v": 1997.1}]}, {"c": [{"v": "DOGE"}, {"v": 1582.6}]}, {"c": [{"v": "ADA"}, {"v": 2243.4}]}, {"c": [{"v": "XLM"}, {"v": 4280.2}]}, {"c": [{"v": "BNB"}, {"v": 16.4}]}, {"c": [{"v": "XRP"}, {"v": 2160.7}]}, {"c": [{"v": "TRX"}, {"v": 4798.7}]}]}