{"cols": [{"id": "as of 18Mar 08:26", "label": "as of 18Mar 08:26", "type": "string"}, {"id": "PnL_D", "label": "PnL_D", "type": "number"}], "rows": [{"c": [{"v": "BNB"}, {"v": 1500.8}]}, {"c": [{"v": "BCH"}, {"v": -763.3}]}, {"c": [{"v": "OM"}, {"v": 786.3}]}, {"c": [{"v": "XRP"}, {"v": -2207.4}]}, {"c": [{"v": "ADA"}, {"v": -886.3}]}, {"c": [{"v": "TON"}, {"v": 799.9}]}, {"c": [{"v": "DOT"}, {"v": -419.3}]}, {"c": [{"v": "HBAR"}, {"v": -255.5}]}, {"c": [{"v": "AVAX"}, {"v": -66.2}]}, {"c": [{"v": "LINK"}, {"v": -102.0}]}, {"c": [{"v": "SUI"}, {"v": 1230.5}]}, {"c": [{"v": "LTC"}, {"v": 1692.5}]}, {"c": [{"v": "DOGE"}, {"v": 2206.3}]}, {"c": [{"v": "ETH"}, {"v": 825.8}]}, {"c": [{"v": "BTC"}, {"v": -9259.1}]}, {"c": [{"v": "ETH"}, {"v": -651.9}]}, {"c": [{"v": "SOL"}, {"v": -583.7}]}, {"c": [{"v": "OM"}, {"v": -53.6}]}, {"c": [{"v": "DOT"}, {"v": 153.3}]}, {"c": [{"v": "SUI"}, {"v": 538.3}]}, {"c": [{"v": "LTC"}, {"v": 514.6}]}, {"c": [{"v": "AVAX"}, {"v": -118.6}]}, {"c": [{"v": "SHIB"}, {"v": 428.0}]}, {"c": [{"v": "HBAR"}, {"v": 376.6}]}, {"c": [{"v": "ADA"}, {"v": 252.3}]}, {"c": [{"v": "XLM"}, {"v": 196.7}]}, {"c": [{"v": "XRP"}, {"v": 751.7}]}, {"c": [{"v": "TON"}, {"v": -627.9}]}, {"c": [{"v": "LINK"}, {"v": -303.9}]}, {"c": [{"v": "DOGE"}, {"v": 1521.2}]}, {"c": [{"v": "BNB"}, {"v": -568.4}]}, {"c": [{"v": "TRX"}, {"v": -804.0}]}]}