{"cols": [{"id": "as of 18Sep 07:23", "label": "as of 18Sep 07:23", "type": "string"}, {"id": "totrade_w", "label": "totrade_w", "type": "number"}], "rows": [{"c": [{"v": "BNB"}, {"v": -6.73}]}, {"c": [{"v": "ADA"}, {"v": -5.88}]}, {"c": [{"v": "DOT"}, {"v": -5.56}]}, {"c": [{"v": "DOGE"}, {"v": -3.23}]}, {"c": [{"v": "1000SHIB"}, {"v": -2.16}]}, {"c": [{"v": "LTC"}, {"v": -1.84}]}, {"c": [{"v": "LINK"}, {"v": -1.31}]}, {"c": [{"v": "SOL"}, {"v": -1.01}]}, {"c": [{"v": "ETH"}, {"v": -0.8}]}, {"c": [{"v": "AVAX"}, {"v": -0.72}]}, {"c": [{"v": "NEAR"}, {"v": -0.66}]}, {"c": [{"v": "BCH"}, {"v": 0.05}]}, {"c": [{"v": "TON"}, {"v": 7.24}]}, {"c": [{"v": "XRP"}, {"v": 9.41}]}, {"c": [{"v": "BTC"}, {"v": 12.74}]}]}