{"cols": [{"id": "as of 27Jul 07:23", "label": "as of 27Jul 07:23", "type": "string"}, {"id": "w% current", "label": "w% current", "type": "number"}, {"id": "w% target", "label": "w% target", "type": "number"}], "rows": [{"c": [{"v": "BTC"}, {"v": 45.51}, {"v": 56.00000000000001}]}, {"c": [{"v": "XRP"}, {"v": 19.12}, {"v": 11.58}]}, {"c": [{"v": "SOL"}, {"v": 17.46}, {"v": 16.05}]}, {"c": [{"v": "ICP"}, {"v": 5.27}, {"v": 0.0}]}, {"c": [{"v": "AVAX"}, {"v": 2.41}, {"v": -0.7000000000000001}]}, {"c": [{"v": "1000PEPE"}, {"v": 2.35}, {"v": 0.37}]}, {"c": [{"v": "ETH"}, {"v": 2.17}, {"v": -0.83}]}, {"c": [{"v": "DOGE"}, {"v": 1.97}, {"v": 10.879999999999999}]}, {"c": [{"v": "TRX"}, {"v": 0.72}, {"v": 4.34}]}, {"c": [{"v": "NEAR"}, {"v": -0.35000000000000003}, {"v": 2.9899999999999998}]}, {"c": [{"v": "LTC"}, {"v": -1.2}, {"v": -1.41}]}, {"c": [{"v": "BCH"}, {"v": -1.6500000000000001}, {"v": -1.41}]}, {"c": [{"v": "BNB"}, {"v": -2.22}, {"v": -0.66}]}, {"c": [{"v": "LINK"}, {"v": -2.37}, {"v": -3.4000000000000004}]}, {"c": [{"v": "ADA"}, {"v": -2.75}, {"v": -4.49}]}, {"c": [{"v": "UNI"}, {"v": -2.81}, {"v": 0.0}]}, {"c": [{"v": "MATIC"}, {"v": -3.38}, {"v": -5.57}]}, {"c": [{"v": "1000SHIB"}, {"v": -3.45}, {"v": -4.590000000000001}]}, {"c": [{"v": "DOT"}, {"v": -5.2}, {"v": -9.91}]}, {"c": [{"v": "TON"}, {"v": -7.6899999999999995}, {"v": -9.91}]}]}