{"cols": [{"id": "as of 29Aug 07:23", "label": "as of 29Aug 07:23", "type": "string"}, {"id": "w% current", "label": "w% current", "type": "number"}, {"id": "w% target", "label": "w% target", "type": "number"}], "rows": [{"c": [{"v": "BTC"}, {"v": 49.96}, {"v": 21.67}]}, {"c": [{"v": "TRX"}, {"v": 10.190000000000001}, {"v": 22.07}]}, {"c": [{"v": "MATIC"}, {"v": 9.53}, {"v": 0.0}]}, {"c": [{"v": "AVAX"}, {"v": 8.469999999999999}, {"v": 12.620000000000001}]}, {"c": [{"v": "NEAR"}, {"v": 5.63}, {"v": 7.17}]}, {"c": [{"v": "XRP"}, {"v": 0.67}, {"v": 1.18}]}, {"c": [{"v": "BNB"}, {"v": 0.5499999999999999}, {"v": 5.57}]}, {"c": [{"v": "LINK"}, {"v": 0.29}, {"v": 6.47}]}, {"c": [{"v": "ETH"}, {"v": -1.5699999999999998}, {"v": -2.5700000000000003}]}, {"c": [{"v": "SOL"}, {"v": -1.66}, {"v": -4.18}]}, {"c": [{"v": "ADA"}, {"v": -2.7}, {"v": -1.9300000000000002}]}, {"c": [{"v": "TON"}, {"v": -3.53}, {"v": -4.01}]}, {"c": [{"v": "LTC"}, {"v": -3.66}, {"v": -2.8899999999999997}]}, {"c": [{"v": "1000SHIB"}, {"v": -3.9699999999999998}, {"v": 3.0700000000000003}]}, {"c": [{"v": "BCH"}, {"v": -4.32}, {"v": -4.41}]}, {"c": [{"v": "DOGE"}, {"v": -4.96}, {"v": -4.590000000000001}]}, {"c": [{"v": "DOT"}, {"v": -5.45}, {"v": -7.049999999999999}]}]}