{"cols": [{"id": "as of 20Mar 09:27", "label": "as of 20Mar 09:27", "type": "string"}, {"id": "PnL_D", "label": "PnL_D", "type": "number"}], "rows": [{"c": [{"v": "BCH"}, {"v": 582.5}]}, {"c": [{"v": "BNB"}, {"v": 4686.8}]}, {"c": [{"v": "XRP"}, {"v": -2919.5}]}, {"c": [{"v": "TON"}, {"v": -226.6}]}, {"c": [{"v": "DOT"}, {"v": -1252.3}]}, {"c": [{"v": "ADA"}, {"v": -1276.3}]}, {"c": [{"v": "OM"}, {"v": 65.7}]}, {"c": [{"v": "SOL"}, {"v": -189.4}]}, {"c": [{"v": "XLM"}, {"v": -190.4}]}, {"c": [{"v": "SUI"}, {"v": 24.7}]}, {"c": [{"v": "LINK"}, {"v": 427.0}]}, {"c": [{"v": "AVAX"}, {"v": 659.1}]}, {"c": [{"v": "DOGE"}, {"v": 1133.6}]}, {"c": [{"v": "ETH"}, {"v": 1744.6}]}, {"c": [{"v": "LTC"}, {"v": 1489.9}]}, {"c": [{"v": "BTC"}, {"v": -8700.0}]}, {"c": [{"v": "ETH"}, {"v": -1548.9}]}, {"c": [{"v": "SOL"}, {"v": -377.3}]}, {"c": [{"v": "BCH"}, {"v": -41.9}]}, {"c": [{"v": "SUI"}, {"v": 22.7}]}, {"c": [{"v": "AVAX"}, {"v": 496.3}]}, {"c": [{"v": "HBAR"}, {"v": 243.7}]}, {"c": [{"v": "LTC"}, {"v": 321.5}]}, {"c": [{"v": "DOT"}, {"v": 260.8}]}, {"c": [{"v": "SHIB"}, {"v": 32.4}]}, {"c": [{"v": "ADA"}, {"v": 359.5}]}, {"c": [{"v": "OM"}, {"v": -23.6}]}, {"c": [{"v": "XRP"}, {"v": 705.8}]}, {"c": [{"v": "XLM"}, {"v": 502.4}]}, {"c": [{"v": "TON"}, {"v": 101.1}]}, {"c": [{"v": "LINK"}, {"v": 1106.2}]}, {"c": [{"v": "DOGE"}, {"v": 967.0}]}, {"c": [{"v": "TRX"}, {"v": 475.4}]}, {"c": [{"v": "BNB"}, {"v": -2041.9}]}]}