{"cols": [{"id": "as of 15Apr 10:23", "label": "as of 15Apr 10:23", "type": "string"}, {"id": "PnL_D", "label": "PnL_D", "type": "number"}], "rows": [{"c": [{"v": "BNB"}, {"v": 3631.6}]}, {"c": [{"v": "BTC"}, {"v": 1188.1}]}, {"c": [{"v": "TON"}, {"v": 4060.6}]}, {"c": [{"v": "BCH"}, {"v": 3649.8}]}, {"c": [{"v": "ICP"}, {"v": 2925.3}]}, {"c": [{"v": "ETH"}, {"v": 1449.9}]}, {"c": [{"v": "DOGE"}, {"v": 793.2}]}, {"c": [{"v": "TRX"}, {"v": 811.2}]}, {"c": [{"v": "LTC"}, {"v": 371.9}]}, {"c": [{"v": "UNI"}, {"v": -364.6}]}, {"c": [{"v": "XRP"}, {"v": -337.2}]}, {"c": [{"v": "AVAX"}, {"v": -547.8}]}, {"c": [{"v": "DOT"}, {"v": -1808.3}]}, {"c": [{"v": "LINK"}, {"v": -1373.5}]}, {"c": [{"v": "ADA"}, {"v": -2372.0}]}, {"c": [{"v": "MATIC"}, {"v": -2498.4}]}, {"c": [{"v": "BTC"}, {"v": 5567.9}]}, {"c": [{"v": "NEAR"}, {"v": -7.9}]}, {"c": [{"v": "ICP"}, {"v": -524.1}]}, {"c": [{"v": "LTC"}, {"v": -222.6}]}, {"c": [{"v": "MATIC"}, {"v": -536.5}]}, {"c": [{"v": "DOT"}, {"v": -485.2}]}, {"c": [{"v": "LINK"}, {"v": -360.8}]}, {"c": [{"v": "TRX"}, {"v": -338.4}]}, {"c": [{"v": "DOGE"}, {"v": -332.3}]}, {"c": [{"v": "BCH"}, {"v": -1007.2}]}, {"c": [{"v": "SHIB"}, {"v": -749.6}]}, {"c": [{"v": "TON"}, {"v": -1053.9}]}, {"c": [{"v": "AVAX"}, {"v": -543.1}]}, {"c": [{"v": "SOL"}, {"v": -535.3}]}, {"c": [{"v": "ADA"}, {"v": -1597.3}]}, {"c": [{"v": "XRP"}, {"v": -980.4}]}, {"c": [{"v": "BNB"}, {"v": -1041.9}]}]}