{"cols": [{"id": "as of 12Aug 21:23", "label": "as of 12Aug 21:23", "type": "string"}, {"id": "PnL_D", "label": "PnL_D", "type": "number"}], "rows": [{"c": [{"v": "XRP"}, {"v": 4341.9}]}, {"c": [{"v": "BTC"}, {"v": 69.5}]}, {"c": [{"v": "SOL"}, {"v": 1264.8}]}, {"c": [{"v": "TRX"}, {"v": -769.1}]}, {"c": [{"v": "BCH"}, {"v": 2396.5}]}, {"c": [{"v": "BNB"}, {"v": 639.0}]}, {"c": [{"v": "NEAR"}, {"v": -284.0}]}, {"c": [{"v": "ADA"}, {"v": -693.5}]}, {"c": [{"v": "AVAX"}, {"v": -884.4}]}, {"c": [{"v": "LINK"}, {"v": -2591.2}]}, {"c": [{"v": "DOT"}, {"v": -310.4}]}, {"c": [{"v": "ETH"}, {"v": -3229.2}]}, {"c": [{"v": "BTC"}, {"v": 277.8}]}, {"c": [{"v": "ETH"}, {"v": 1778.2}]}, {"c": [{"v": "LINK"}, {"v": -735.3}]}, {"c": [{"v": "BCH"}, {"v": -867.5}]}, {"c": [{"v": "XRP"}, {"v": -850.9}]}, {"c": [{"v": "AVAX"}, {"v": -939.6}]}, {"c": [{"v": "SOL"}, {"v": -393.6}]}, {"c": [{"v": "TON"}, {"v": -235.0}]}, {"c": [{"v": "DOGE"}, {"v": -2247.2}]}, {"c": [{"v": "DOT"}, {"v": -212.0}]}, {"c": [{"v": "SHIB"}, {"v": -904.7}]}, {"c": [{"v": "TRX"}, {"v": 502.9}]}, {"c": [{"v": "BNB"}, {"v": -936.1}]}, {"c": [{"v": "ADA"}, {"v": -945.6}]}]}