{"cols": [{"id": "as of 16Nov 12:26", "label": "as of 16Nov 12:26", "type": "string"}, {"id": "totrade_w", "label": "totrade_w", "type": "number"}], "rows": [{"c": [{"v": "ETH"}, {"v": -10.44}]}, {"c": [{"v": "SOL"}, {"v": -10.32}]}, {"c": [{"v": "1000SHIB"}, {"v": -6.75}]}, {"c": [{"v": "ADA"}, {"v": -5.85}]}, {"c": [{"v": "DOGE"}, {"v": -3.06}]}, {"c": [{"v": "SUI"}, {"v": -2.92}]}, {"c": [{"v": "BTC"}, {"v": -2.64}]}, {"c": [{"v": "NEAR"}, {"v": -1.53}]}, {"c": [{"v": "UNI"}, {"v": -1.48}]}, {"c": [{"v": "BNB"}, {"v": -0.84}]}, {"c": [{"v": "AVAX"}, {"v": -0.82}]}, {"c": [{"v": "1000PEPE"}, {"v": -0.66}]}, {"c": [{"v": "TRX"}, {"v": -0.51}]}, {"c": [{"v": "TON"}, {"v": -0.3}]}, {"c": [{"v": "LINK"}, {"v": -0.03}]}, {"c": [{"v": "BCH"}, {"v": 0.02}]}, {"c": [{"v": "LTC"}, {"v": 0.2}]}, {"c": [{"v": "DOT"}, {"v": 0.41}]}, {"c": [{"v": "XLM"}, {"v": 8.05}]}, {"c": [{"v": "XRP"}, {"v": 19.24}]}]}