{"cols": [{"id": "as of 19Jul 10:22", "label": "as of 19Jul 10:22", "type": "string"}, {"id": "totrade_w", "label": "totrade_w", "type": "number"}], "rows": [{"c": [{"v": "BTC"}, {"v": -24.41}]}, {"c": [{"v": "ICP"}, {"v": -8.74}]}, {"c": [{"v": "ADA"}, {"v": -5.79}]}, {"c": [{"v": "XRP"}, {"v": -3.62}]}, {"c": [{"v": "DOT"}, {"v": -2.64}]}, {"c": [{"v": "LTC"}, {"v": -2.21}]}, {"c": [{"v": "UNI"}, {"v": -1.1}]}, {"c": [{"v": "LINK"}, {"v": -0.99}]}, {"c": [{"v": "1000SHIB"}, {"v": -0.77}]}, {"c": [{"v": "MATIC"}, {"v": 0.33}]}, {"c": [{"v": "BNB"}, {"v": 0.96}]}, {"c": [{"v": "TON"}, {"v": 1.0}]}, {"c": [{"v": "AVAX"}, {"v": 1.04}]}, {"c": [{"v": "DOGE"}, {"v": 1.67}]}, {"c": [{"v": "1000PEPE"}, {"v": 3.34}]}, {"c": [{"v": "BCH"}, {"v": 4.81}]}, {"c": [{"v": "NEAR"}, {"v": 4.99}]}, {"c": [{"v": "TRX"}, {"v": 6.54}]}, {"c": [{"v": "SOL"}, {"v": 13.21}]}]}