{"cols": [{"id": "as of 18May 16:25", "label": "as of 18May 16:25", "type": "string"}, {"id": "PnL_D", "label": "PnL_D", "type": "number"}], "rows": [{"c": [{"v": "SOL"}, {"v": 5404.2}]}, {"c": [{"v": "LINK"}, {"v": 2514.9}]}, {"c": [{"v": "NEAR"}, {"v": -3479.0}]}, {"c": [{"v": "TON"}, {"v": -4931.2}]}, {"c": [{"v": "TRX"}, {"v": -874.7}]}, {"c": [{"v": "SHIB"}, {"v": -620.8}]}, {"c": [{"v": "AVAX"}, {"v": 760.1}]}, {"c": [{"v": "ADA"}, {"v": 4.7}]}, {"c": [{"v": "DOGE"}, {"v": -136.9}]}, {"c": [{"v": "BTC"}, {"v": -14.8}]}, {"c": [{"v": "LTC"}, {"v": 16.1}]}, {"c": [{"v": "ICP"}, {"v": -428.7}]}, {"c": [{"v": "XRP"}, {"v": 26.8}]}, {"c": [{"v": "MATIC"}, {"v": -11.2}]}, {"c": [{"v": "BCH"}, {"v": -575.0}]}, {"c": [{"v": "BNB"}, {"v": 127.1}]}, {"c": [{"v": "ETH"}, {"v": -304.9}]}, {"c": [{"v": "BTC"}, {"v": -940.4}]}, {"c": [{"v": "NEAR"}, {"v": 190.5}]}, {"c": [{"v": "MATIC"}, {"v": -6.3}]}, {"c": [{"v": "BCH"}, {"v": -328.2}]}, {"c": [{"v": "DOT"}, {"v": 131.5}]}, {"c": [{"v": "LINK"}, {"v": -157.7}]}, {"c": [{"v": "LTC"}, {"v": 30.8}]}, {"c": [{"v": "ICP"}, {"v": -555.8}]}, {"c": [{"v": "TRX"}, {"v": 185.6}]}, {"c": [{"v": "AVAX"}, {"v": -844.9}]}, {"c": [{"v": "SHIB"}, {"v": 731.1}]}, {"c": [{"v": "SOL"}, {"v": -714.8}]}, {"c": [{"v": "DOGE"}, {"v": 743.7}]}, {"c": [{"v": "ADA"}, {"v": -20.4}]}, {"c": [{"v": "TON"}, {"v": 1288.8}]}, {"c": [{"v": "BNB"}, {"v": 211.8}]}, {"c": [{"v": "XRP"}, {"v": 109.0}]}]}