{"cols": [{"id": "as of 22Jan 10:22", "label": "as of 22Jan 10:22", "type": "string"}, {"id": "PnL_D", "label": "PnL_D", "type": "number"}], "rows": [{"c": [{"v": "BNB"}, {"v": -718.3}]}, {"c": [{"v": "TRX"}, {"v": -161.1}]}, {"c": [{"v": "ETH"}, {"v": -886.6}]}, {"c": [{"v": "LINK"}, {"v": -499.5}]}, {"c": [{"v": "ETC"}, {"v": -925.5}]}, {"c": [{"v": "ICP"}, {"v": -293.1}]}, {"c": [{"v": "DOGE"}, {"v": -174.0}]}, {"c": [{"v": "LTC"}, {"v": -159.6}]}, {"c": [{"v": "BTC"}, {"v": 42.6}]}, {"c": [{"v": "ADA"}, {"v": 119.8}]}, {"c": [{"v": "ATOM"}, {"v": 131.2}]}, {"c": [{"v": "DOT"}, {"v": 166.9}]}, {"c": [{"v": "XRP"}, {"v": 203.8}]}, {"c": [{"v": "MATIC"}, {"v": 257.3}]}, {"c": [{"v": "AVAX"}, {"v": 413.4}]}, {"c": [{"v": "BTC"}, {"v": -2137.6}]}, {"c": [{"v": "ICP"}, {"v": 56.9}]}, {"c": [{"v": "UNI"}, {"v": 91.8}]}, {"c": [{"v": "MATIC"}, {"v": 103.0}]}, {"c": [{"v": "DOT"}, {"v": 84.9}]}, {"c": [{"v": "LINK"}, {"v": 56.9}]}, {"c": [{"v": "BCH"}, {"v": 20.0}]}, {"c": [{"v": "SHIB"}, {"v": 0.1}]}, {"c": [{"v": "LTC"}, {"v": 120.1}]}, {"c": [{"v": "SOL"}, {"v": 284.7}]}, {"c": [{"v": "AVAX"}, {"v": 430.6}]}, {"c": [{"v": "ADA"}, {"v": 260.5}]}, {"c": [{"v": "DOGE"}, {"v": 379.4}]}, {"c": [{"v": "XRP"}, {"v": 329.8}]}, {"c": [{"v": "TRX"}, {"v": 56.1}]}, {"c": [{"v": "BNB"}, {"v": 205.0}]}]}