{"cols": [{"id": "as of 01Oct 21:23", "label": "as of 01Oct 21:23", "type": "string"}, {"id": "PnL_D", "label": "PnL_D", "type": "number"}], "rows": [{"c": [{"v": "SUI"}, {"v": -6639.6}]}, {"c": [{"v": "SHIB"}, {"v": -14023.5}]}, {"c": [{"v": "1000PEPE"}, {"v": -12881.6}]}, {"c": [{"v": "NEAR"}, {"v": -12607.7}]}, {"c": [{"v": "AVAX"}, {"v": -5067.5}]}, {"c": [{"v": "DOGE"}, {"v": -1493.7}]}, {"c": [{"v": "BTC"}, {"v": -555.1}]}, {"c": [{"v": "UNI"}, {"v": -886.1}]}, {"c": [{"v": "ICP"}, {"v": -648.6}]}, {"c": [{"v": "BNB"}, {"v": 428.3}]}, {"c": [{"v": "TRX"}, {"v": 185.2}]}, {"c": [{"v": "BCH"}, {"v": 839.8}]}, {"c": [{"v": "BTC"}, {"v": -31153.5}]}, {"c": [{"v": "ETH"}, {"v": -4812.6}]}, {"c": [{"v": "SOL"}, {"v": -1244.2}]}, {"c": [{"v": "SUI"}, {"v": 315.6}]}, {"c": [{"v": "DOT"}, {"v": 1035.5}]}, {"c": [{"v": "NEAR"}, {"v": 1429.7}]}, {"c": [{"v": "BCH"}, {"v": 1176.6}]}, {"c": [{"v": "LTC"}, {"v": 1114.9}]}, {"c": [{"v": "SHIB"}, {"v": 2915.2}]}, {"c": [{"v": "LINK"}, {"v": 2909.6}]}, {"c": [{"v": "AVAX"}, {"v": 3497.3}]}, {"c": [{"v": "DOGE"}, {"v": 3421.3}]}, {"c": [{"v": "ADA"}, {"v": 3172.7}]}, {"c": [{"v": "TON"}, {"v": 3666.9}]}, {"c": [{"v": "TRX"}, {"v": 812.4}]}, {"c": [{"v": "BNB"}, {"v": 2163.8}]}, {"c": [{"v": "XRP"}, {"v": 1294.1}]}]}