{"cols": [{"id": "as of 18Nov 20:24", "label": "as of 18Nov 20:24", "type": "string"}, {"id": "totrade_w", "label": "totrade_w", "type": "number"}], "rows": [{"c": [{"v": "BTC"}, {"v": -10.66}]}, {"c": [{"v": "ETH"}, {"v": -9.85}]}, {"c": [{"v": "ADA"}, {"v": -6.34}]}, {"c": [{"v": "SOL"}, {"v": -5.72}]}, {"c": [{"v": "1000PEPE"}, {"v": -3.0}]}, {"c": [{"v": "DOGE"}, {"v": -0.88}]}, {"c": [{"v": "1000SHIB"}, {"v": -0.68}]}, {"c": [{"v": "SUI"}, {"v": -0.26}]}, {"c": [{"v": "NEAR"}, {"v": -0.13}]}, {"c": [{"v": "LTC"}, {"v": -0.01}]}, {"c": [{"v": "DOT"}, {"v": 0.01}]}, {"c": [{"v": "BNB"}, {"v": 0.06}]}, {"c": [{"v": "BCH"}, {"v": 0.07}]}, {"c": [{"v": "TRX"}, {"v": 0.09}]}, {"c": [{"v": "LINK"}, {"v": 0.1}]}, {"c": [{"v": "TON"}, {"v": 0.14}]}, {"c": [{"v": "APT"}, {"v": 0.16}]}, {"c": [{"v": "AVAX"}, {"v": 0.31}]}, {"c": [{"v": "XLM"}, {"v": 0.7}]}, {"c": [{"v": "XRP"}, {"v": 2.09}]}, {"c": [{"v": "HBAR"}, {"v": 9.15}]}]}