{"cols": [{"id": "as of 19Jul 16:23", "label": "as of 19Jul 16:23", "type": "string"}, {"id": "PnL_D", "label": "PnL_D", "type": "number"}], "rows": [{"c": [{"v": "XRP"}, {"v": 675.3}]}, {"c": [{"v": "NEAR"}, {"v": 14265.4}]}, {"c": [{"v": "ADA"}, {"v": 4856.2}]}, {"c": [{"v": "SOL"}, {"v": 9335.3}]}, {"c": [{"v": "ICP"}, {"v": 3948.0}]}, {"c": [{"v": "TRX"}, {"v": 153.1}]}, {"c": [{"v": "1000PEPE"}, {"v": 1790.5}]}, {"c": [{"v": "DOT"}, {"v": 326.5}]}, {"c": [{"v": "BCH"}, {"v": -157.6}]}, {"c": [{"v": "DOGE"}, {"v": -459.8}]}, {"c": [{"v": "BNB"}, {"v": -538.9}]}, {"c": [{"v": "AVAX"}, {"v": -340.4}]}, {"c": [{"v": "LINK"}, {"v": -661.8}]}, {"c": [{"v": "LTC"}, {"v": -561.5}]}, {"c": [{"v": "TON"}, {"v": -154.6}]}, {"c": [{"v": "MATIC"}, {"v": -1244.4}]}, {"c": [{"v": "UNI"}, {"v": -1780.2}]}, {"c": [{"v": "BTC"}, {"v": 25090.8}]}, {"c": [{"v": "NEAR"}, {"v": -578.3}]}, {"c": [{"v": "BCH"}, {"v": -236.4}]}, {"c": [{"v": "LINK"}, {"v": -441.2}]}, {"c": [{"v": "LTC"}, {"v": -285.7}]}, {"c": [{"v": "MATIC"}, {"v": -259.5}]}, {"c": [{"v": "UNI"}, {"v": -295.0}]}, {"c": [{"v": "SHIB"}, {"v": -746.1}]}, {"c": [{"v": "SOL"}, {"v": -2504.3}]}, {"c": [{"v": "XRP"}, {"v": -74.1}]}, {"c": [{"v": "DOGE"}, {"v": -1618.8}]}, {"c": [{"v": "TRX"}, {"v": -67.4}]}, {"c": [{"v": "BNB"}, {"v": -1717.3}]}, {"c": [{"v": "DOT"}, {"v": -1264.7}]}, {"c": [{"v": "ADA"}, {"v": -1134.9}]}, {"c": [{"v": "TON"}, {"v": -143.1}]}, {"c": [{"v": "AVAX"}, {"v": -1021.2}]}]}