{"cols": [{"id": "as of 25Jan 13:24", "label": "as of 25Jan 13:24", "type": "string"}, {"id": "totrade_w", "label": "totrade_w", "type": "number"}], "rows": [{"c": [{"v": "SOL"}, {"v": -6.93}]}, {"c": [{"v": "XRP"}, {"v": -6.55}]}, {"c": [{"v": "ETH"}, {"v": -5.64}]}, {"c": [{"v": "LINK"}, {"v": -5.34}]}, {"c": [{"v": "XLM"}, {"v": -4.46}]}, {"c": [{"v": "UNI"}, {"v": -3.32}]}, {"c": [{"v": "APT"}, {"v": -2.06}]}, {"c": [{"v": "DOGE"}, {"v": -1.87}]}, {"c": [{"v": "SUI"}, {"v": -1.58}]}, {"c": [{"v": "BNB"}, {"v": -1.24}]}, {"c": [{"v": "HBAR"}, {"v": -0.77}]}, {"c": [{"v": "BCH"}, {"v": -0.55}]}, {"c": [{"v": "AVAX"}, {"v": -0.54}]}, {"c": [{"v": "1000PEPE"}, {"v": -0.06}]}, {"c": [{"v": "1000SHIB"}, {"v": 0.22}]}, {"c": [{"v": "BTC"}, {"v": 0.56}]}, {"c": [{"v": "TRX"}, {"v": 0.97}]}, {"c": [{"v": "ADA"}, {"v": 1.1}]}, {"c": [{"v": "DOT"}, {"v": 1.65}]}, {"c": [{"v": "TON"}, {"v": 1.98}]}, {"c": [{"v": "ONDO"}, {"v": 2.1}]}, {"c": [{"v": "LTC"}, {"v": 7.88}]}]}