{"cols": [{"id": "as of 05Aug 18:24", "label": "as of 05Aug 18:24", "type": "string"}, {"id": "RtD%", "label": "RtD%", "type": "number"}], "rows": [{"c": [{"v": "XRP"}, {"v": -7.4}]}, {"c": [{"v": "BTC"}, {"v": -7.5}]}, {"c": [{"v": "BCH"}, {"v": -8.1}]}, {"c": [{"v": "SOL"}, {"v": -5.1}]}, {"c": [{"v": "KAS"}, {"v": -10.2}]}, {"c": [{"v": "BNB"}, {"v": -7.3}]}, {"c": [{"v": "TRX"}, {"v": -4.0}]}, {"c": [{"v": "LTC"}, {"v": -10.0}]}, {"c": [{"v": "MATIC"}, {"v": -9.1}]}, {"c": [{"v": "SHIB"}, {"v": -2.4}]}, {"c": [{"v": "ETH"}, {"v": -9.9}]}, {"c": [{"v": "ADA"}, {"v": -8.5}]}, {"c": [{"v": "NEAR"}, {"v": -14.8}]}, {"c": [{"v": "AVAX"}, {"v": -7.5}]}, {"c": [{"v": "TON"}, {"v": -12.2}]}, {"c": [{"v": "LINK"}, {"v": -13.9}]}, {"c": [{"v": "DOT"}, {"v": -11.0}]}, {"c": [{"v": "BTC"}, {"v": -7.5}]}, {"c": [{"v": "ETH"}, {"v": -9.9}]}, {"c": [{"v": "LTC"}, {"v": -10.0}]}, {"c": [{"v": "NEAR"}, {"v": -14.8}]}, {"c": [{"v": "LINK"}, {"v": -13.9}]}, {"c": [{"v": "BCH"}, {"v": -8.1}]}, {"c": [{"v": "DOT"}, {"v": -11.0}]}, {"c": [{"v": "SHIB"}, {"v": -2.4}]}, {"c": [{"v": "SOL"}, {"v": -5.1}]}, {"c": [{"v": "AVAX"}, {"v": -7.5}]}, {"c": [{"v": "DOGE"}, {"v": -8.7}]}, {"c": [{"v": "XRP"}, {"v": -7.4}]}, {"c": [{"v": "BNB"}, {"v": -7.3}]}, {"c": [{"v": "TON"}, {"v": -12.2}]}, {"c": [{"v": "ADA"}, {"v": -8.5}]}, {"c": [{"v": "TRX"}, {"v": -4.0}]}]}