{"cols": [{"id": "as of 04May 07:23", "label": "as of 04May 07:23", "type": "string"}, {"id": "w% current", "label": "w% current", "type": "number"}, {"id": "w% target", "label": "w% target", "type": "number"}], "rows": [{"c": [{"v": "TRX"}, {"v": 21.86}, {"v": 22.59}]}, {"c": [{"v": "BTC"}, {"v": 21.790000000000003}, {"v": 42.08}]}, {"c": [{"v": "NEAR"}, {"v": 10.26}, {"v": 9.24}]}, {"c": [{"v": "DOT"}, {"v": 7.82}, {"v": 8.23}]}, {"c": [{"v": "MATIC"}, {"v": 6.23}, {"v": -0.37}]}, {"c": [{"v": "TON"}, {"v": 2.45}, {"v": 6.13}]}, {"c": [{"v": "BNB"}, {"v": 2.16}, {"v": -4.3}]}, {"c": [{"v": "LTC"}, {"v": 0.79}, {"v": -1.41}]}, {"c": [{"v": "XRP"}, {"v": -0.2}, {"v": -1.22}]}, {"c": [{"v": "ICP"}, {"v": -0.38999999999999996}, {"v": -3.38}]}, {"c": [{"v": "1000SHIB"}, {"v": -1.0}, {"v": 2.88}]}, {"c": [{"v": "BCH"}, {"v": -3.0300000000000002}, {"v": -4.25}]}, {"c": [{"v": "AVAX"}, {"v": -3.27}, {"v": -4.05}]}, {"c": [{"v": "SOL"}, {"v": -4.21}, {"v": -5.87}]}, {"c": [{"v": "DOGE"}, {"v": -4.2700000000000005}, {"v": -1.54}]}, {"c": [{"v": "LINK"}, {"v": -4.37}, {"v": -4.9799999999999995}]}, {"c": [{"v": "ADA"}, {"v": -4.3999999999999995}, {"v": -5.82}]}]}