{"cols": [{"id": "as of 22Mar 15:25", "label": "as of 22Mar 15:25", "type": "string"}, {"id": "RtD%", "label": "RtD%", "type": "number"}], "rows": [{"c": [{"v": "BNB"}, {"v": -1.6}]}, {"c": [{"v": "BCH"}, {"v": 0.2}]}, {"c": [{"v": "TON"}, {"v": 1.2}]}, {"c": [{"v": "XRP"}, {"v": -0.3}]}, {"c": [{"v": "DOT"}, {"v": -1.7}]}, {"c": [{"v": "ADA"}, {"v": -0.3}]}, {"c": [{"v": "XLM"}, {"v": -0.9}]}, {"c": [{"v": "TRX"}, {"v": 0.5}]}, {"c": [{"v": "LINK"}, {"v": 1.7}]}, {"c": [{"v": "AVAX"}, {"v": 1.2}]}, {"c": [{"v": "HBAR"}, {"v": -0.9}]}, {"c": [{"v": "SUI"}, {"v": 1.0}]}, {"c": [{"v": "DOGE"}, {"v": 0.2}]}, {"c": [{"v": "ETH"}, {"v": 1.0}]}, {"c": [{"v": "LTC"}, {"v": -0.1}]}, {"c": [{"v": "BTC"}, {"v": -0.0}]}, {"c": [{"v": "ETH"}, {"v": 1.0}]}, {"c": [{"v": "SOL"}, {"v": 0.3}]}, {"c": [{"v": "SUI"}, {"v": 1.0}]}, {"c": [{"v": "OM"}, {"v": 1.7}]}, {"c": [{"v": "AVAX"}, {"v": 1.2}]}, {"c": [{"v": "HBAR"}, {"v": -0.9}]}, {"c": [{"v": "DOT"}, {"v": -1.7}]}, {"c": [{"v": "LTC"}, {"v": -0.1}]}, {"c": [{"v": "ADA"}, {"v": -0.3}]}, {"c": [{"v": "SHIB"}, {"v": 1.8}]}, {"c": [{"v": "XRP"}, {"v": -0.3}]}, {"c": [{"v": "LINK"}, {"v": 1.7}]}, {"c": [{"v": "TON"}, {"v": 1.2}]}, {"c": [{"v": "XLM"}, {"v": -0.9}]}, {"c": [{"v": "DOGE"}, {"v": 0.2}]}, {"c": [{"v": "BNB"}, {"v": -1.6}]}, {"c": [{"v": "TRX"}, {"v": 0.5}]}]}