{"cols": [{"id": "as of 09Jan 11:21", "label": "as of 09Jan 11:21", "type": "string"}, {"id": "w%", "label": "w%", "type": "number"}], "rows": [{"c": [{"v": "BTC"}, {"v": 28.2}]}, {"c": [{"v": "ICP"}, {"v": 7.9}]}, {"c": [{"v": "NEAR"}, {"v": 6.1}]}, {"c": [{"v": "INJ"}, {"v": 6.0}]}, {"c": [{"v": "OP"}, {"v": 5.3}]}, {"c": [{"v": "BNB"}, {"v": 2.5}]}, {"c": [{"v": "BCH"}, {"v": 0.7}]}, {"c": [{"v": "TRX"}, {"v": -0.9}]}, {"c": [{"v": "MATIC"}, {"v": -1.2}]}, {"c": [{"v": "SHIB"}, {"v": -1.2}]}, {"c": [{"v": "DOT"}, {"v": -1.8}]}, {"c": [{"v": "ATOM"}, {"v": -1.9}]}, {"c": [{"v": "UNI"}, {"v": -2.4}]}, {"c": [{"v": "XLM"}, {"v": -2.6}]}, {"c": [{"v": "ADA"}, {"v": -2.9}]}, {"c": [{"v": "LTC"}, {"v": -4.2}]}, {"c": [{"v": "XRP"}, {"v": -7.1}]}, {"c": [{"v": "DOGE"}, {"v": -7.7}]}]}