{"cols": [{"id": "as of 05Feb 09:22", "label": "as of 05Feb 09:22", "type": "string"}, {"id": "totrade_w", "label": "totrade_w", "type": "number"}], "rows": [{"c": [{"v": "ETH"}, {"v": -3.0}]}, {"c": [{"v": "1000SHIB"}, {"v": -1.86}]}, {"c": [{"v": "UNI"}, {"v": -1.51}]}, {"c": [{"v": "MATIC"}, {"v": -1.37}]}, {"c": [{"v": "DOGE"}, {"v": -1.26}]}, {"c": [{"v": "BCH"}, {"v": -1.22}]}, {"c": [{"v": "LTC"}, {"v": -1.16}]}, {"c": [{"v": "BNB"}, {"v": -1.03}]}, {"c": [{"v": "ATOM"}, {"v": -0.84}]}, {"c": [{"v": "ETC"}, {"v": -0.51}]}, {"c": [{"v": "LINK"}, {"v": -0.41}]}, {"c": [{"v": "XRP"}, {"v": -0.2}]}, {"c": [{"v": "ADA"}, {"v": 0.83}]}, {"c": [{"v": "DOT"}, {"v": 2.97}]}, {"c": [{"v": "TRX"}, {"v": 3.02}]}, {"c": [{"v": "SOL"}, {"v": 3.29}]}, {"c": [{"v": "BTC"}, {"v": 3.74}]}, {"c": [{"v": "AVAX"}, {"v": 4.54}]}]}