{"cols": [{"id": "as of 04Jul 12:23", "label": "as of 04Jul 12:23", "type": "string"}, {"id": "w% current", "label": "w% current", "type": "number"}, {"id": "w% target", "label": "w% target", "type": "number"}], "rows": [{"c": [{"v": "BTC"}, {"v": 44.76}, {"v": 22.5}]}, {"c": [{"v": "TON"}, {"v": 13.020000000000001}, {"v": 3.46}]}, {"c": [{"v": "TRX"}, {"v": 6.61}, {"v": 22.13}]}, {"c": [{"v": "SOL"}, {"v": 5.25}, {"v": 3.08}]}, {"c": [{"v": "DOT"}, {"v": 4.35}, {"v": 3.1300000000000003}]}, {"c": [{"v": "XRP"}, {"v": 3.9899999999999998}, {"v": 8.790000000000001}]}, {"c": [{"v": "UNI"}, {"v": 1.5599999999999998}, {"v": 0.0}]}, {"c": [{"v": "AVAX"}, {"v": -0.6}, {"v": 3.2099999999999995}]}, {"c": [{"v": "LTC"}, {"v": -0.76}, {"v": 1.25}]}, {"c": [{"v": "ETH"}, {"v": -0.8999999999999999}, {"v": -0.83}]}, {"c": [{"v": "ADA"}, {"v": -2.04}, {"v": 13.459999999999999}]}, {"c": [{"v": "BNB"}, {"v": -3.19}, {"v": -4.79}]}, {"c": [{"v": "MATIC"}, {"v": -3.6799999999999997}, {"v": -5.75}]}, {"c": [{"v": "BCH"}, {"v": -3.9}, {"v": -3.6700000000000004}]}, {"c": [{"v": "NEAR"}, {"v": -3.9800000000000004}, {"v": -4.2}]}, {"c": [{"v": "DOGE"}, {"v": -5.47}, {"v": -6.87}]}, {"c": [{"v": "1000SHIB"}, {"v": -6.239999999999999}, {"v": -8.12}]}]}