{"cols": [{"id": "as of 05Sep 18:23", "label": "as of 05Sep 18:23", "type": "string"}, {"id": "w% current", "label": "w% current", "type": "number"}, {"id": "w% target", "label": "w% target", "type": "number"}], "rows": [{"c": [{"v": "BTC"}, {"v": 38.2}, {"v": -0.9299999999999999}]}, {"c": [{"v": "TRX"}, {"v": 25.840000000000003}, {"v": 20.0}]}, {"c": [{"v": "LTC"}, {"v": 19.78}, {"v": 17.78}]}, {"c": [{"v": "XRP"}, {"v": 10.79}, {"v": 14.13}]}, {"c": [{"v": "AAVE"}, {"v": 8.88}, {"v": 0.0}]}, {"c": [{"v": "FET"}, {"v": 4.83}, {"v": 0.0}]}, {"c": [{"v": "AVAX"}, {"v": 4.83}, {"v": 8.4}]}, {"c": [{"v": "LINK"}, {"v": 3.4799999999999995}, {"v": 0.9400000000000001}]}, {"c": [{"v": "UNI"}, {"v": 2.13}, {"v": 0.0}]}, {"c": [{"v": "SUI"}, {"v": 1.69}, {"v": 0.0}]}, {"c": [{"v": "FTM"}, {"v": 1.46}, {"v": 0.0}]}, {"c": [{"v": "BNB"}, {"v": 1.1199999999999999}, {"v": 1.3}]}, {"c": [{"v": "1000FLOKI"}, {"v": 1.01}, {"v": 0.0}]}, {"c": [{"v": "SOL"}, {"v": 0.0}, {"v": -6.05}]}, {"c": [{"v": "1000PEPE"}, {"v": -1.01}, {"v": 0.0}]}, {"c": [{"v": "KAS"}, {"v": -1.1199999999999999}, {"v": 0.0}]}, {"c": [{"v": "DOGE"}, {"v": -1.69}, {"v": 9.26}]}, {"c": [{"v": "TON"}, {"v": -1.7999999999999998}, {"v": 0.0}]}, {"c": [{"v": "MKR"}, {"v": -2.25}, {"v": 0.0}]}, {"c": [{"v": "1000SHIB"}, {"v": -2.7}, {"v": 6.569999999999999}]}, {"c": [{"v": "BCH"}, {"v": -2.92}, {"v": -3.2399999999999998}]}, {"c": [{"v": "ATOM"}, {"v": -2.92}, {"v": 0.0}]}, {"c": [{"v": "ADA"}, {"v": -2.92}, {"v": 0.37}]}, {"c": [{"v": "ETH"}, {"v": -4.2700000000000005}, {"v": -5.55}]}, {"c": [{"v": "DOT"}, {"v": -8.88}, {"v": -6.94}]}]}