{"cols": [{"id": "as of 30May 14:53", "label": "as of 30May 14:53", "type": "string"}, {"id": "RtD%", "label": "RtD%", "type": "number"}], "rows": [{"c": [{"v": "XRP"}, {"v": 1.1}]}, {"c": [{"v": "TRX"}, {"v": 0.4}]}, {"c": [{"v": "LTC"}, {"v": 1.6}]}, {"c": [{"v": "ETH"}, {"v": 0.8}]}, {"c": [{"v": "MATIC"}, {"v": 0.0}]}, {"c": [{"v": "SOL"}, {"v": 3.2}]}, {"c": [{"v": "XMR"}, {"v": -1.0}]}, {"c": [{"v": "BNB"}, {"v": 0.4}]}, {"c": [{"v": "ATOM"}, {"v": 1.1}]}, {"c": [{"v": "UNI"}, {"v": 1.4}]}, {"c": [{"v": "BCH"}, {"v": 0.0}]}, {"c": [{"v": "ETC"}, {"v": 0.0}]}, {"c": [{"v": "AVAX"}, {"v": 1.1}]}, {"c": [{"v": "DOGE"}, {"v": -0.6}]}, {"c": [{"v": "SHIB"}, {"v": 0.1}]}, {"c": [{"v": "ICP"}, {"v": 0.2}]}]}